[{"family":"MaterialIcons","fonts":[{"asset":"fonts/MaterialIcons-Regular.otf"}]},{"family":"Roboto_Custom","fonts":[{"weight":900,"asset":"fonts/Roboto-Black.ttf"},{"weight":700,"asset":"fonts/Roboto-Bold.ttf"},{"weight":500,"asset":"fonts/Roboto-Medium.ttf"},{"weight":400,"asset":"fonts/Roboto-Regular.ttf"},{"weight":300,"asset":"fonts/Roboto-Light.ttf"},{"weight":100,"asset":"fonts/Roboto-Thin.ttf"},{"weight":900,"style":"italic","asset":"fonts/Roboto-BlackItalic.ttf"},{"weight":700,"style":"italic","asset":"fonts/Roboto-BoldItalic.ttf"},{"weight":500,"style":"italic","asset":"fonts/Roboto-MediumItalic.ttf"},{"weight":400,"style":"italic","asset":"fonts/Roboto-Italic.ttf"},{"weight":300,"style":"italic","asset":"fonts/Roboto-LightItalic.ttf"},{"weight":100,"style":"italic","asset":"fonts/Roboto-ThinItalic.ttf"}]},{"family":"packages/amplify_authenticator/SocialIcons","fonts":[{"asset":"packages/amplify_authenticator/assets/social-buttons/SocialIcons.ttf"}]},{"family":"packages/cupertino_icons/CupertinoIcons","fonts":[{"asset":"packages/cupertino_icons/assets/CupertinoIcons.ttf"}]}]